{
    "chart_title": "Daily Water vs. Exercise Time",
    "data_points": [
        {
            "label": "Low Daily Water (0.5L)",
            "value": 30
        },
	{
            "label": "Low Daily Water (1.0L)",
            "value": 55
        },
	{
            "label": "Low Daily Water (2.0L)",
            "value": 90
        },
        {
            "label": "Average Daily Water(2.5L)",
            "value": 105
        },
        {
            "label": "High Daily Water(3.0L)",
            "value": 110
        }
    ]
}